[
    {
        "exchange": "zb",
        "nativeInstrument": "1000hokk_qc",
        "nativeBaseSymbol": "1000hokk",
        "nativeQuoteSymbol": "qc",
        "underlying": "1000hokk",
        "active": false,
        "limitsAmountMax": null,
        "limitsAmountMin": 100.0,
        "limitsCostMax": null,
        "limitsCostMin": 5.0,
        "limitsLeverageMax": null,
        "limitsLeverageMin": null,
        "limitsMarketMax": null,
        "limitsMarketMin": null,
        "limitsPriceMax": null,
        "limitsPriceMin": null,
        "precisionAmount": 0.0,
        "precisionBase": null,
        "precisionCost": null,
        "precisionPrice": 1e-09,
        "precisionQuote": null,
        "normalizedInstrument": "1000hokk_qc",
        "normalizedSymbol": "1000hokk",
        "assetName": "Hokkaidu Inu",
        "assetArcId": "AMB:100000000950",
        "instrumentType": "spot"
    }
]