[
    {
        "exchange": "binance",
        "nativeInstrument": "VANRYTRY",
        "nativeBaseSymbol": "VANRY",
        "nativeQuoteSymbol": "TRY",
        "underlying": "VANRY",
        "active": true,
        "limitsAmountMax": 9222449.0,
        "limitsAmountMin": 1.0,
        "limitsCostMax": null,
        "limitsCostMin": 0.0,
        "limitsLeverageMax": null,
        "limitsLeverageMin": null,
        "limitsMarketMax": 90097.5875,
        "limitsMarketMin": 0.0,
        "limitsPriceMax": 10000.0,
        "limitsPriceMin": 0.001,
        "precisionAmount": 1.0,
        "precisionBase": 1e-08,
        "precisionCost": null,
        "precisionPrice": 0.001,
        "precisionQuote": 1e-08,
        "normalizedInstrument": "vanry_try",
        "normalizedSymbol": "vanry",
        "assetName": "Vanar Chain",
        "assetArcId": "AMB:VAN000003084",
        "instrumentType": "spot"
    },
    {
        "exchange": "binance",
        "nativeInstrument": "VANRYBTC",
        "nativeBaseSymbol": "VANRY",
        "nativeQuoteSymbol": "BTC",
        "underlying": "VANRY",
        "active": true,
        "limitsAmountMax": 46116860414.0,
        "limitsAmountMin": 1.0,
        "limitsCostMax": null,
        "limitsCostMin": 0.0,
        "limitsLeverageMax": null,
        "limitsLeverageMin": null,
        "limitsMarketMax": 117020.00833333,
        "limitsMarketMin": 0.0,
        "limitsPriceMax": 1.0,
        "limitsPriceMin": 1e-08,
        "precisionAmount": 1.0,
        "precisionBase": 1e-08,
        "precisionCost": null,
        "precisionPrice": 1e-08,
        "precisionQuote": 1e-08,
        "normalizedInstrument": "vanry_btc",
        "normalizedSymbol": "vanry",
        "assetName": "Vanar Chain",
        "assetArcId": "AMB:VAN000003084",
        "instrumentType": "spot"
    },
    {
        "exchange": "binance",
        "nativeInstrument": "VANRYUSDT",
        "nativeBaseSymbol": "VANRY",
        "nativeQuoteSymbol": "USDT",
        "underlying": "VANRY",
        "active": true,
        "limitsAmountMax": 92141578.0,
        "limitsAmountMin": 1.0,
        "limitsCostMax": null,
        "limitsCostMin": 0.0,
        "limitsLeverageMax": null,
        "limitsLeverageMin": null,
        "limitsMarketMax": 941062.975,
        "limitsMarketMin": 0.0,
        "limitsPriceMax": 1000.0,
        "limitsPriceMin": 1e-05,
        "precisionAmount": 1.0,
        "precisionBase": 1e-08,
        "precisionCost": null,
        "precisionPrice": 1e-05,
        "precisionQuote": 1e-08,
        "normalizedInstrument": "vanry_usdt",
        "normalizedSymbol": "vanry",
        "assetName": "Vanar Chain",
        "assetArcId": "AMB:VAN000003084",
        "instrumentType": "spot"
    }
]