[
    {
        "exchange": "mexc",
        "nativeInstrument": "SERUSDT",
        "nativeBaseSymbol": "SER",
        "nativeQuoteSymbol": "USDT",
        "underlying": "ser",
        "active": true,
        "limitsAmountMax": null,
        "limitsAmountMin": null,
        "limitsCostMax": null,
        "limitsCostMin": null,
        "limitsLeverageMax": null,
        "limitsLeverageMin": null,
        "limitsMarketMax": null,
        "limitsMarketMin": null,
        "limitsPriceMax": null,
        "limitsPriceMin": null,
        "precisionAmount": 1e-05,
        "precisionBase": 0.01,
        "precisionCost": null,
        "precisionPrice": null,
        "precisionQuote": 1e-07,
        "normalizedInstrument": "ser_usdt",
        "normalizedSymbol": "ser",
        "assetName": "Ser Token",
        "assetArcId": "AMB:SER000002168",
        "instrumentType": "spot"
    }
]