[
    {
        "exchange": "mexc",
        "nativeInstrument": "EMZUSDT",
        "nativeBaseSymbol": "EMZ",
        "nativeQuoteSymbol": "USDT",
        "underlying": "emz",
        "active": false,
        "limitsAmountMax": null,
        "limitsAmountMin": null,
        "limitsCostMax": null,
        "limitsCostMin": null,
        "limitsLeverageMax": null,
        "limitsLeverageMin": null,
        "limitsMarketMax": null,
        "limitsMarketMin": null,
        "limitsPriceMax": null,
        "limitsPriceMin": null,
        "precisionAmount": 1e-05,
        "precisionBase": 0.01,
        "precisionCost": null,
        "precisionPrice": null,
        "precisionQuote": 1e-08,
        "normalizedInstrument": "emz_usdt",
        "normalizedSymbol": "emz",
        "assetName": "Emartzon",
        "assetArcId": "AMB:EMZ000001633",
        "instrumentType": "spot"
    }
]