[
    {
        "arcPairId": "AMB:ALG000000012_AMB:BTC000000000",
        "normalizedPair": "algo_btc",
        "normalizedSymbol": "algo",
        "nativePair": "tALGBTC",
        "exchange": "bitfinex",
        "assetName": "Algorand",
        "assetArcId": "AMB:ALG000000012",
        "quoteArcId": "AMB:BTC000000000",
        "collectedPair": "algo_btc",
        "instrumentType": "spot"
    },
    {
        "arcPairId": "AMB:ALG000000012_AMB:USD000000949",
        "normalizedPair": "algo_usd",
        "normalizedSymbol": "algo",
        "nativePair": "tALGUSD",
        "exchange": "bitfinex",
        "assetName": "Algorand",
        "assetArcId": "AMB:ALG000000012",
        "quoteArcId": "AMB:USD000000949",
        "collectedPair": "algo_usd",
        "instrumentType": "spot"
    },
    {
        "arcPairId": "AMB:ALG000000012_AMB:USD000000335",
        "normalizedPair": "algo_usdt",
        "normalizedSymbol": "algo",
        "nativePair": "tALGUST",
        "exchange": "bitfinex",
        "assetName": "Algorand",
        "assetArcId": "AMB:ALG000000012",
        "quoteArcId": "AMB:USD000000335",
        "collectedPair": "algo_usdt",
        "instrumentType": "spot"
    }
]
