[
    {
        "exchange": "bybit",
        "nativeInstrument": "GNSUSDT",
        "nativeBaseSymbol": "GNS",
        "nativeQuoteSymbol": "USDT",
        "underlying": "GNS",
        "active": true,
        "limitsAmountMax": null,
        "limitsAmountMin": null,
        "limitsCostMax": null,
        "limitsCostMin": null,
        "limitsLeverageMax": null,
        "limitsLeverageMin": null,
        "limitsMarketMax": null,
        "limitsMarketMin": null,
        "limitsPriceMax": null,
        "limitsPriceMin": null,
        "precisionAmount": null,
        "precisionBase": null,
        "precisionCost": null,
        "precisionPrice": null,
        "precisionQuote": null,
        "normalizedInstrument": "gns_usdt",
        "normalizedSymbol": "gns",
        "assetName": "Gains Network",
        "assetArcId": "AMB:GNS000000153",
        "instrumentType": "spot"
    }
]