[
    {
        "arcPairId": "AMB:SHI000000293_AMB:USD000000333",
        "normalizedPair": "shib_usdc",
        "normalizedSymbol": "shib",
        "nativePair": "SHIB_USDC",
        "exchange": "poloniex",
        "assetName": "SHIBA INU",
        "assetArcId": "AMB:SHI000000293",
        "quoteArcId": "AMB:USD000000333",
        "collectedPair": "shib_usdc",
        "instrumentType": "spot"
    },
    {
        "arcPairId": "AMB:SHI000000293_AMB:USD000000841",
        "normalizedPair": "shib_usdd",
        "normalizedSymbol": "shib",
        "nativePair": "SHIB_USDD",
        "exchange": "poloniex",
        "assetName": "SHIBA INU",
        "assetArcId": "AMB:SHI000000293",
        "quoteArcId": "AMB:USD000000841",
        "collectedPair": "shib_usdd",
        "instrumentType": "spot"
    },
    {
        "arcPairId": "AMB:SHI000000293_AMB:USD000000335",
        "normalizedPair": "shib_usdt",
        "normalizedSymbol": "shib",
        "nativePair": "SHIB_USDT",
        "exchange": "poloniex",
        "assetName": "SHIBA INU",
        "assetArcId": "AMB:SHI000000293",
        "quoteArcId": "AMB:USD000000335",
        "collectedPair": "shib_usdt",
        "instrumentType": "spot"
    }
]