[
    {
        "arcPairId": "AMB:RLC000000280_AMB:BTC000000000",
        "normalizedPair": "rlc_btc",
        "normalizedSymbol": "rlc",
        "nativePair": "RLC-BTC",
        "exchange": "gdax",
        "assetName": "iExec RLC",
        "assetArcId": "AMB:RLC000000280",
        "quoteArcId": "AMB:BTC000000000",
        "collectedPair": "rlc_btc",
        "instrumentType": "spot"
    },
    {
        "arcPairId": "AMB:RLC000000280_AMB:USD000000949",
        "normalizedPair": "rlc_usd",
        "normalizedSymbol": "rlc",
        "nativePair": "RLC-USD",
        "exchange": "gdax",
        "assetName": "iExec RLC",
        "assetArcId": "AMB:RLC000000280",
        "quoteArcId": "AMB:USD000000949",
        "collectedPair": "rlc_usd",
        "instrumentType": "spot"
    }
]