[
    {
        "arcPairId": "AMB:USD000000949_AMB:USD000000333",
        "normalizedPair": "usd_usdc",
        "normalizedSymbol": "usd",
        "nativePair": "usd-usdc",
        "exchange": "lmax",
        "assetName": "United States Dollar",
        "assetArcId": "AMB:USD000000949",
        "quoteArcId": "AMB:USD000000333",
        "collectedPair": "usd_usdc",
        "instrumentType": "spot"
    },
    {
        "arcPairId": "AMB:USD000000949_AMB:USD000000335",
        "normalizedPair": "usd_usdt",
        "normalizedSymbol": "usd",
        "nativePair": "usd-usdt",
        "exchange": "lmax",
        "assetName": "United States Dollar",
        "assetArcId": "AMB:USD000000949",
        "quoteArcId": "AMB:USD000000335",
        "collectedPair": "usd_usdt",
        "instrumentType": "spot"
    }
]