[
    {
        "arcPairId": "AMB:ZEN000000370_AMB:BTC000000000",
        "normalizedPair": "zen_btc",
        "normalizedSymbol": "zen",
        "nativePair": "ZENBTC",
        "exchange": "binance",
        "assetName": "Horizen",
        "assetArcId": "AMB:ZEN000000370",
        "quoteArcId": "AMB:BTC000000000",
        "collectedPair": "zen_btc",
        "instrumentType": "spot"
    },
    {
        "arcPairId": "AMB:ZEN000000370_AMB:ETH000000000",
        "normalizedPair": "zen_eth",
        "normalizedSymbol": "zen",
        "nativePair": "ZENETH",
        "exchange": "binance",
        "assetName": "Horizen",
        "assetArcId": "AMB:ZEN000000370",
        "quoteArcId": "AMB:ETH000000000",
        "collectedPair": "zen_eth",
        "instrumentType": "spot"
    },
    {
        "arcPairId": "AMB:ZEN000000370_AMB:USD000000335",
        "normalizedPair": "zen_usdt",
        "normalizedSymbol": "zen",
        "nativePair": "ZENUSDT",
        "exchange": "binance",
        "assetName": "Horizen",
        "assetArcId": "AMB:ZEN000000370",
        "quoteArcId": "AMB:USD000000335",
        "collectedPair": "zen_usdt",
        "instrumentType": "spot"
    }
]