{
    "assetSymbol": "luis",
    "assetName": "Tongue Cat",
    "assetArcId": "AMB:LUI000000000",
    "website": "https://www.tonguecatluis.xyz/",
    "whitePaperUrl": "/how-to-buy/LUIS?utm_source=mexc&utm_medium=tokenifoLUIS&utm_campaign=tokeninfo",
    "classificationTags": [],
    "miscellaneous": {
        "relatedLinks": [
            "https://github.com/amberdata/arc/blob/main//packages/instruments/type=spot/asset_name=Tongue Cat/arc_id=AMB:LUI000000000/exchange=mexc/data.json"
        ]
    }
}
