[
    {
        "exchange": "bybit",
        "nativeInstrument": "DSRUNUSDT",
        "nativeBaseSymbol": "DSRUN",
        "nativeQuoteSymbol": "USDT",
        "underlying": "DSRUN",
        "active": true,
        "limitsAmountMax": null,
        "limitsAmountMin": null,
        "limitsCostMax": null,
        "limitsCostMin": null,
        "limitsLeverageMax": null,
        "limitsLeverageMin": null,
        "limitsMarketMax": null,
        "limitsMarketMin": null,
        "limitsPriceMax": null,
        "limitsPriceMin": null,
        "precisionAmount": null,
        "precisionBase": null,
        "precisionCost": null,
        "precisionPrice": null,
        "precisionQuote": null,
        "normalizedInstrument": "dsrun_usdt",
        "normalizedSymbol": "dsrun",
        "assetName": "Derby Stars",
        "assetArcId": "AMB:DSR000001029",
        "instrumentType": "spot"
    }
]