[
    {
        "arcPairId": "AMB:DOT000000105_AMB:BNB000000055",
        "normalizedPair": "dot_bnb",
        "normalizedSymbol": "dot",
        "nativePair": "DOTBNB",
        "exchange": "binance",
        "assetName": "Polkadot",
        "assetArcId": "AMB:DOT000000105",
        "quoteArcId": "AMB:BNB000000055",
        "collectedPair": "dot_bnb",
        "instrumentType": "spot"
    },
    {
        "arcPairId": "AMB:DOT000000105_AMB:BRL000002486",
        "normalizedPair": "dot_brl",
        "normalizedSymbol": "dot",
        "nativePair": "DOTBRL",
        "exchange": "binance",
        "assetName": "Polkadot",
        "assetArcId": "AMB:DOT000000105",
        "quoteArcId": "AMB:BRL000002486",
        "collectedPair": "dot_brl",
        "instrumentType": "spot"
    },
    {
        "arcPairId": "AMB:DOT000000105_AMB:BTC000000000",
        "normalizedPair": "dot_btc",
        "normalizedSymbol": "dot",
        "nativePair": "DOTBTC",
        "exchange": "binance",
        "assetName": "Polkadot",
        "assetArcId": "AMB:DOT000000105",
        "quoteArcId": "AMB:BTC000000000",
        "collectedPair": "dot_btc",
        "instrumentType": "spot"
    },
    {
        "arcPairId": "AMB:DOT000000105_AMB:BUS000000067",
        "normalizedPair": "dot_busd",
        "normalizedSymbol": "dot",
        "nativePair": "DOTBUSD",
        "exchange": "binance",
        "assetName": "Polkadot",
        "assetArcId": "AMB:DOT000000105",
        "quoteArcId": "AMB:BUS000000067",
        "collectedPair": "dot_busd",
        "instrumentType": "spot"
    },
    {
        "arcPairId": "AMB:DOT000000105_AMB:ETH000000000",
        "normalizedPair": "dot_eth",
        "normalizedSymbol": "dot",
        "nativePair": "DOTETH",
        "exchange": "binance",
        "assetName": "Polkadot",
        "assetArcId": "AMB:DOT000000105",
        "quoteArcId": "AMB:ETH000000000",
        "collectedPair": "dot_eth",
        "instrumentType": "spot"
    },
    {
        "arcPairId": "AMB:DOT000000105_AMB:EUR000000120",
        "normalizedPair": "dot_eur",
        "normalizedSymbol": "dot",
        "nativePair": "DOTEUR",
        "exchange": "binance",
        "assetName": "Polkadot",
        "assetArcId": "AMB:DOT000000105",
        "quoteArcId": "AMB:EUR000000120",
        "collectedPair": "dot_eur",
        "instrumentType": "spot"
    },
    {
        "arcPairId": "AMB:DOT000000105_AMB:GBP000000144",
        "normalizedPair": "dot_gbp",
        "normalizedSymbol": "dot",
        "nativePair": "DOTGBP",
        "exchange": "binance",
        "assetName": "Polkadot",
        "assetArcId": "AMB:DOT000000105",
        "quoteArcId": "AMB:GBP000000144",
        "collectedPair": "dot_gbp",
        "instrumentType": "spot"
    },
    {
        "arcPairId": "AMB:DOT000000105_AMB:RUB000000000",
        "normalizedPair": "dot_rub",
        "normalizedSymbol": "dot",
        "nativePair": "DOTRUB",
        "exchange": "binance",
        "assetName": "Polkadot",
        "assetArcId": "AMB:DOT000000105",
        "quoteArcId": "AMB:RUB000000000",
        "collectedPair": "dot_rub",
        "instrumentType": "spot"
    },
    {
        "arcPairId": "AMB:DOT000000105_AMB:TRY000000940",
        "normalizedPair": "dot_try",
        "normalizedSymbol": "dot",
        "nativePair": "DOTTRY",
        "exchange": "binance",
        "assetName": "Polkadot",
        "assetArcId": "AMB:DOT000000105",
        "quoteArcId": "AMB:TRY000000940",
        "collectedPair": "dot_try",
        "instrumentType": "spot"
    },
    {
        "arcPairId": "AMB:DOT000000105_AMB:USD000000335",
        "normalizedPair": "dot_usdt",
        "normalizedSymbol": "dot",
        "nativePair": "DOTUSDT",
        "exchange": "binance",
        "assetName": "Polkadot",
        "assetArcId": "AMB:DOT000000105",
        "quoteArcId": "AMB:USD000000335",
        "collectedPair": "dot_usdt",
        "instrumentType": "spot"
    }
]
