[
    {
        "exchange": "mexc",
        "nativeInstrument": "HUSUSDT",
        "nativeBaseSymbol": "HUS",
        "nativeQuoteSymbol": "USDT",
        "underlying": "hus",
        "active": true,
        "limitsAmountMax": null,
        "limitsAmountMin": null,
        "limitsCostMax": null,
        "limitsCostMin": null,
        "limitsLeverageMax": null,
        "limitsLeverageMin": null,
        "limitsMarketMax": null,
        "limitsMarketMin": null,
        "limitsPriceMax": null,
        "limitsPriceMin": null,
        "precisionAmount": 1e-05,
        "precisionBase": 0.01,
        "precisionCost": null,
        "precisionPrice": null,
        "precisionQuote": 1e-07,
        "normalizedInstrument": "hus_usdt",
        "normalizedSymbol": "hus",
        "assetName": "Husky.AI",
        "assetArcId": "AMB:HUS000001767",
        "instrumentType": "spot"
    }
]