[
    {
        "arcPairId": "AMB:VIB000000340_AMB:BTC000000000",
        "normalizedPair": "vib_btc",
        "normalizedSymbol": "vib",
        "nativePair": "VIBBTC",
        "exchange": "binance",
        "assetName": "Viberate",
        "assetArcId": "AMB:VIB000000340",
        "quoteArcId": "AMB:BTC000000000",
        "collectedPair": "vib_btc",
        "instrumentType": "spot"
    },
    {
        "arcPairId": "AMB:VIB000000340_AMB:BUS000000067",
        "normalizedPair": "vib_busd",
        "normalizedSymbol": "vib",
        "nativePair": "VIBBUSD",
        "exchange": "binance",
        "assetName": "Viberate",
        "assetArcId": "AMB:VIB000000340",
        "quoteArcId": "AMB:BUS000000067",
        "collectedPair": "vib_busd",
        "instrumentType": "spot"
    },
    {
        "arcPairId": "AMB:VIB000000340_AMB:USD000000335",
        "normalizedPair": "vib_usdt",
        "normalizedSymbol": "vib",
        "nativePair": "VIBUSDT",
        "exchange": "binance",
        "assetName": "Viberate",
        "assetArcId": "AMB:VIB000000340",
        "quoteArcId": "AMB:USD000000335",
        "collectedPair": "vib_usdt",
        "instrumentType": "spot"
    }
]
