[
    {
        "exchange": "zb",
        "nativeInstrument": "eth_btc",
        "nativeBaseSymbol": "eth",
        "nativeQuoteSymbol": "btc",
        "underlying": "eth",
        "active": false,
        "limitsAmountMax": null,
        "limitsAmountMin": 0.001,
        "limitsCostMax": null,
        "limitsCostMin": 0.0001,
        "limitsLeverageMax": null,
        "limitsLeverageMin": null,
        "limitsMarketMax": null,
        "limitsMarketMin": null,
        "limitsPriceMax": null,
        "limitsPriceMin": null,
        "precisionAmount": 0.001,
        "precisionBase": null,
        "precisionCost": null,
        "precisionPrice": 1e-06,
        "precisionQuote": null,
        "normalizedInstrument": "eth_btc",
        "normalizedSymbol": "eth",
        "assetName": "Ether",
        "assetArcId": "AMB:ETH000000000",
        "instrumentType": "spot"
    },
    {
        "exchange": "zb",
        "nativeInstrument": "eth_qc",
        "nativeBaseSymbol": "eth",
        "nativeQuoteSymbol": "qc",
        "underlying": "eth",
        "active": false,
        "limitsAmountMax": null,
        "limitsAmountMin": 0.001,
        "limitsCostMax": null,
        "limitsCostMin": 5.0,
        "limitsLeverageMax": null,
        "limitsLeverageMin": null,
        "limitsMarketMax": null,
        "limitsMarketMin": null,
        "limitsPriceMax": null,
        "limitsPriceMin": null,
        "precisionAmount": 0.001,
        "precisionBase": null,
        "precisionCost": null,
        "precisionPrice": 0.01,
        "precisionQuote": null,
        "normalizedInstrument": "eth_qc",
        "normalizedSymbol": "eth",
        "assetName": "Ether",
        "assetArcId": "AMB:ETH000000000",
        "instrumentType": "spot"
    },
    {
        "exchange": "zb",
        "nativeInstrument": "eth_usdc",
        "nativeBaseSymbol": "eth",
        "nativeQuoteSymbol": "usdc",
        "underlying": "eth",
        "active": false,
        "limitsAmountMax": null,
        "limitsAmountMin": 1e-05,
        "limitsCostMax": null,
        "limitsCostMin": 0.1,
        "limitsLeverageMax": null,
        "limitsLeverageMin": null,
        "limitsMarketMax": null,
        "limitsMarketMin": null,
        "limitsPriceMax": null,
        "limitsPriceMin": null,
        "precisionAmount": 1e-05,
        "precisionBase": null,
        "precisionCost": null,
        "precisionPrice": 0.01,
        "precisionQuote": null,
        "normalizedInstrument": "eth_usdc",
        "normalizedSymbol": "eth",
        "assetName": "Ether",
        "assetArcId": "AMB:ETH000000000",
        "instrumentType": "spot"
    },
    {
        "exchange": "zb",
        "nativeInstrument": "eth_usdt",
        "nativeBaseSymbol": "eth",
        "nativeQuoteSymbol": "usdt",
        "underlying": "eth",
        "active": false,
        "limitsAmountMax": null,
        "limitsAmountMin": 0.001,
        "limitsCostMax": null,
        "limitsCostMin": 1.0,
        "limitsLeverageMax": null,
        "limitsLeverageMin": null,
        "limitsMarketMax": null,
        "limitsMarketMin": null,
        "limitsPriceMax": null,
        "limitsPriceMin": null,
        "precisionAmount": 0.001,
        "precisionBase": null,
        "precisionCost": null,
        "precisionPrice": 0.01,
        "precisionQuote": null,
        "normalizedInstrument": "eth_usdt",
        "normalizedSymbol": "eth",
        "assetName": "Ether",
        "assetArcId": "AMB:ETH000000000",
        "instrumentType": "spot"
    }
]