[
    {
        "arcPairId": "AMB:PER000000248_AMB:BTC000000000",
        "normalizedPair": "perp_btc",
        "normalizedSymbol": "perp",
        "nativePair": "PERPBTC",
        "exchange": "binance",
        "assetName": "Perpetual Protocol",
        "assetArcId": "AMB:PER000000248",
        "quoteArcId": "AMB:BTC000000000",
        "collectedPair": "perp_btc",
        "instrumentType": "spot"
    },
    {
        "arcPairId": "AMB:PER000000248_AMB:BUS000000067",
        "normalizedPair": "perp_busd",
        "normalizedSymbol": "perp",
        "nativePair": "PERPBUSD",
        "exchange": "binance",
        "assetName": "Perpetual Protocol",
        "assetArcId": "AMB:PER000000248",
        "quoteArcId": "AMB:BUS000000067",
        "collectedPair": "perp_busd",
        "instrumentType": "spot"
    },
    {
        "arcPairId": "AMB:PER000000248_AMB:USD000000335",
        "normalizedPair": "perp_usdt",
        "normalizedSymbol": "perp",
        "nativePair": "PERPUSDT",
        "exchange": "binance",
        "assetName": "Perpetual Protocol",
        "assetArcId": "AMB:PER000000248",
        "quoteArcId": "AMB:USD000000335",
        "collectedPair": "perp_usdt",
        "instrumentType": "spot"
    }
]