[
    {
        "exchange": "binance",
        "nativeInstrument": "1000SATSTRY",
        "nativeBaseSymbol": "1000SATS",
        "nativeQuoteSymbol": "TRY",
        "underlying": "1000SATS",
        "active": true,
        "limitsAmountMax": 36348600000.0,
        "limitsAmountMin": 1.0,
        "limitsCostMax": null,
        "limitsCostMin": 0.0,
        "limitsLeverageMax": null,
        "limitsLeverageMin": null,
        "limitsMarketMax": 108022059.75,
        "limitsMarketMin": 0.0,
        "limitsPriceMax": 1.0,
        "limitsPriceMin": 1e-06,
        "precisionAmount": 1.0,
        "precisionBase": 0.01,
        "precisionCost": null,
        "precisionPrice": 1e-06,
        "precisionQuote": 1e-08,
        "normalizedInstrument": "1000sats_try",
        "normalizedSymbol": "1000sats",
        "assetName": "1000SATS (Ordinals)",
        "assetArcId": "AMB:100000002781",
        "instrumentType": "spot"
    },
    {
        "exchange": "binance",
        "nativeInstrument": "1000SATSFDUSD",
        "nativeBaseSymbol": "1000SATS",
        "nativeQuoteSymbol": "FDUSD",
        "underlying": "1000SATS",
        "active": true,
        "limitsAmountMax": 36348600000.0,
        "limitsAmountMin": 1.0,
        "limitsCostMax": null,
        "limitsCostMin": 0.0,
        "limitsLeverageMax": null,
        "limitsLeverageMin": null,
        "limitsMarketMax": 61665060.6,
        "limitsMarketMin": 0.0,
        "limitsPriceMax": 1.0,
        "limitsPriceMin": 1e-07,
        "precisionAmount": 1.0,
        "precisionBase": 0.01,
        "precisionCost": null,
        "precisionPrice": 1e-07,
        "precisionQuote": 1e-08,
        "normalizedInstrument": "1000sats_fdusd",
        "normalizedSymbol": "1000sats",
        "assetName": "1000SATS (Ordinals)",
        "assetArcId": "AMB:100000002781",
        "instrumentType": "spot"
    },
    {
        "exchange": "binance",
        "nativeInstrument": "1000SATSUSDT",
        "nativeBaseSymbol": "1000SATS",
        "nativeQuoteSymbol": "USDT",
        "underlying": "1000SATS",
        "active": true,
        "limitsAmountMax": 36348600000.0,
        "limitsAmountMin": 1.0,
        "limitsCostMax": null,
        "limitsCostMin": 0.0,
        "limitsLeverageMax": null,
        "limitsLeverageMin": null,
        "limitsMarketMax": 1000535854.55,
        "limitsMarketMin": 0.0,
        "limitsPriceMax": 1.0,
        "limitsPriceMin": 1e-07,
        "precisionAmount": 1.0,
        "precisionBase": 0.01,
        "precisionCost": null,
        "precisionPrice": 1e-07,
        "precisionQuote": 1e-08,
        "normalizedInstrument": "1000sats_usdt",
        "normalizedSymbol": "1000sats",
        "assetName": "1000SATS (Ordinals)",
        "assetArcId": "AMB:100000002781",
        "instrumentType": "spot"
    }
]