[
    {
        "exchange": "binanceus",
        "nativeInstrument": "DIAUSDT",
        "nativeBaseSymbol": "DIA",
        "nativeQuoteSymbol": "USDT",
        "underlying": "DIA",
        "active": true,
        "limitsAmountMax": 922327.0,
        "limitsAmountMin": 0.1,
        "limitsCostMax": null,
        "limitsCostMin": 1.0,
        "limitsLeverageMax": null,
        "limitsLeverageMin": null,
        "limitsMarketMax": 2849.09208333,
        "limitsMarketMin": 0.0,
        "limitsPriceMax": 10000.0,
        "limitsPriceMin": 0.0001,
        "precisionAmount": 0.1,
        "precisionBase": 1e-08,
        "precisionCost": null,
        "precisionPrice": 0.0001,
        "precisionQuote": 1e-08,
        "normalizedInstrument": "dia_usdt",
        "normalizedSymbol": "dia",
        "assetName": "DIA",
        "assetArcId": "AMB:DIA000000101",
        "instrumentType": "spot"
    }
]