{
    "assetSymbol": "zkb",
    "assetName": "ZKBase",
    "assetArcId": "AMB:ZKB000002753",
    "website": "https://zkbase.org/",
    "whitePaperUrl": null,
    "classificationTags": [],
    "miscellaneous": {
        "relatedLinks": [
            "https://github.com/amberdata/arc/blob/main/packages/instruments/type=spot/asset_name=ZKBase/arc_id=AMB:ZKB000002753/exchange=huobi/data.json",
            "https://github.com/amberdata/arc/blob/main/packages/instruments/type=spot/asset_name=ZKBase/arc_id=AMB:ZKB000002753/exchange=mexc/data.json"
        ]
    }
}