[
    {
        "exchange": "huobi",
        "nativeInstrument": "KSM-USD",
        "underlying": "KSM",
        "expiration": null,
        "active": false,
        "contractSize": 10.0,
        "contractType": "perpetual",
        "marginType": "inverse",
        "limitsAmountMax": null,
        "limitsAmountMin": null,
        "limitsCostMax": null,
        "limitsLeverageMax": null,
        "limitsLeverageMin": null,
        "limitsMarketMax": null,
        "limitsMarketMin": null,
        "limitsPriceMax": null,
        "limitsPriceMin": null,
        "precisionAmount": null,
        "precisionBase": null,
        "precisionPrice": null,
        "precisionQuote": null,
        "settleAsset": null,
        "normalizedInstrument": "KSM-USD",
        "instrumentType": "futures",
        "assetArcId": "AMB:KSM000000187",
        "assetName": "Kusama"
    },
    {
        "exchange": "huobi",
        "nativeInstrument": "KSM-USDT",
        "underlying": "KSM",
        "expiration": null,
        "active": true,
        "contractSize": 0.1,
        "contractType": "perpetual",
        "marginType": "linear",
        "limitsAmountMax": null,
        "limitsAmountMin": null,
        "limitsCostMax": null,
        "limitsLeverageMax": null,
        "limitsLeverageMin": null,
        "limitsMarketMax": null,
        "limitsMarketMin": null,
        "limitsPriceMax": null,
        "limitsPriceMin": null,
        "precisionAmount": null,
        "precisionBase": null,
        "precisionPrice": null,
        "precisionQuote": null,
        "settleAsset": null,
        "normalizedInstrument": "KSM-USDT",
        "instrumentType": "futures",
        "assetArcId": "AMB:KSM000000187",
        "assetName": "Kusama"
    }
]