[
    {
        "exchange": "bybit",
        "nativeInstrument": "ENSUSDT",
        "nativeBaseSymbol": "ENS",
        "nativeQuoteSymbol": "USDT",
        "underlying": "ENS",
        "active": true,
        "limitsAmountMax": null,
        "limitsAmountMin": null,
        "limitsCostMax": null,
        "limitsCostMin": null,
        "limitsLeverageMax": null,
        "limitsLeverageMin": null,
        "limitsMarketMax": null,
        "limitsMarketMin": null,
        "limitsPriceMax": null,
        "limitsPriceMin": null,
        "precisionAmount": null,
        "precisionBase": null,
        "precisionCost": null,
        "precisionPrice": null,
        "precisionQuote": null,
        "normalizedInstrument": "ens_usdt",
        "normalizedSymbol": "ens",
        "assetName": "Ethereum Name Service",
        "assetArcId": "AMB:ENS000000113",
        "instrumentType": "spot"
    }
]