[
    {
        "exchange": "ftx",
        "nativeInstrument": "KNCBEAR/USD",
        "nativeBaseSymbol": "KNCBEAR",
        "nativeQuoteSymbol": "USD",
        "underlying": "KNCBEAR",
        "active": false,
        "limitsAmountMax": null,
        "limitsAmountMin": 1000000.0,
        "limitsCostMax": null,
        "limitsCostMin": null,
        "limitsLeverageMax": 20.0,
        "limitsLeverageMin": 1.0,
        "limitsMarketMax": null,
        "limitsMarketMin": null,
        "limitsPriceMax": null,
        "limitsPriceMin": null,
        "precisionAmount": 1000000.0,
        "precisionBase": null,
        "precisionCost": null,
        "precisionPrice": 1e-08,
        "precisionQuote": null,
        "normalizedInstrument": "kncbear_usd",
        "normalizedSymbol": "kncbear",
        "assetName": "3X Short Kyber Network Token",
        "assetArcId": "AMB:KNC000002577",
        "instrumentType": "spot"
    },
    {
        "exchange": "ftx",
        "nativeInstrument": "KNCBEAR/USDT",
        "nativeBaseSymbol": "KNCBEAR",
        "nativeQuoteSymbol": "USDT",
        "underlying": "KNCBEAR",
        "active": false,
        "limitsAmountMax": null,
        "limitsAmountMin": 1000000.0,
        "limitsCostMax": null,
        "limitsCostMin": null,
        "limitsLeverageMax": 20.0,
        "limitsLeverageMin": 1.0,
        "limitsMarketMax": null,
        "limitsMarketMin": null,
        "limitsPriceMax": null,
        "limitsPriceMin": null,
        "precisionAmount": 1000000.0,
        "precisionBase": null,
        "precisionCost": null,
        "precisionPrice": 1e-08,
        "precisionQuote": null,
        "normalizedInstrument": "kncbear_usdt",
        "normalizedSymbol": "kncbear",
        "assetName": "3X Short Kyber Network Token",
        "assetArcId": "AMB:KNC000002577",
        "instrumentType": "spot"
    }
]