{
    "assetSymbol": "memerats",
    "assetName": "Memerats",
    "assetArcId": "AMB:MEM000002933",
    "website": "https://ratstoken.space/",
    "whitePaperUrl": "/how-to-buy/MEMERATS?utm_source=mexc&utm_medium=tokenifoMEMERATS&utm_campaign=tokeninfo",
    "classificationTags": [
        "Meme"
    ],
    "miscellaneous": {
        "relatedLinks": [
            "https://github.com/amberdata/arc/blob/main//packages/instruments/type=spot/asset_name=Memerats/arc_id=AMB:MEM000002933/exchange=mexc/data.json"
        ]
    }
}
