[
    {
        "exchange": "mexc",
        "nativeInstrument": "XAUSDT",
        "nativeBaseSymbol": "XA",
        "nativeQuoteSymbol": "USDT",
        "underlying": "xa",
        "active": true,
        "limitsAmountMax": null,
        "limitsAmountMin": null,
        "limitsCostMax": null,
        "limitsCostMin": null,
        "limitsLeverageMax": null,
        "limitsLeverageMin": null,
        "limitsMarketMax": null,
        "limitsMarketMin": null,
        "limitsPriceMax": null,
        "limitsPriceMin": null,
        "precisionAmount": 1e-05,
        "precisionBase": 0.01,
        "precisionCost": null,
        "precisionPrice": null,
        "precisionQuote": 1e-16,
        "normalizedInstrument": "xa_usdt",
        "normalizedSymbol": "xa",
        "assetName": "XLV",
        "assetArcId": "AMB:XAA000000000",
        "instrumentType": "spot"
    }
]